trafficgram_bot_sdk/__init__.py
trafficgram_bot_sdk/actions.py
trafficgram_bot_sdk/ads.py
trafficgram_bot_sdk/logging_utils.py
trafficgram_bot_sdk/main.py
trafficgram_bot_sdk/py.typed
trafficgram_bot_sdk/types.py
trafficgram_bot_sdk/utils.py
trafficgram_bot_sdk-1.0.0.dist-info/METADATA
trafficgram_bot_sdk-1.0.0.dist-info/WHEEL
trafficgram_bot_sdk-1.0.0.dist-info/top_level.txt
trafficgram_bot_sdk-1.0.0.dist-info/RECORD
