Metadata-Version: 2.4
Name: trafficgram_bot_sdk
Version: 1.0.0
Summary: Trafficgram SDK
Author-email: trafficgram <targetgram.ai@proton.me>
License: MIT
Requires-Python: >=3.10
Requires-Dist: aiogram>=3.20.0.post0
Requires-Dist: asyncio>=3.4.3
Requires-Dist: fastapi>=0.115.13
Requires-Dist: jinja2>=3.1.6
Requires-Dist: pre-commit>=4.2.0
Requires-Dist: pytest>=8.4.1
Requires-Dist: pytest-asyncio>=1.0.0
Requires-Dist: python-dotenv>=1.1.0
Requires-Dist: ruff>=0.12.0
Requires-Dist: uvicorn>=0.34.3
